exposure_fusion.py
exposure_fusion-0.1.1.dist-info/DESCRIPTION.rst
exposure_fusion-0.1.1.dist-info/METADATA
exposure_fusion-0.1.1.dist-info/metadata.json
exposure_fusion-0.1.1.dist-info/RECORD
exposure_fusion-0.1.1.dist-info/top_level.txt
exposure_fusion-0.1.1.dist-info/WHEEL
