Metadata-Version: 2.0
Name: exposure-fusion
Version: 0.1.1
Summary: Exposure fusion of multiple images
Home-page: https://github.com/arpesenti/exposure_fusion
Author: Armando Pesenti Gritti
Author-email: arpesenti@gmail.com
License: GPL
Keywords: computer vision exposure fusion
Platform: UNKNOWN
Classifier: Development Status :: 3 - Alpha
Classifier: Intended Audience :: Developers
Classifier: License :: OSI Approved :: GNU General Public License v2 (GPLv2)
Classifier: Programming Language :: Python :: 2.6
Classifier: Programming Language :: Python :: 2.7
Classifier: Programming Language :: Python :: 3
Classifier: Programming Language :: Python :: 3.2
Classifier: Programming Language :: Python :: 3.3
Classifier: Programming Language :: Python :: 3.4
Requires-Dist: numpy
